ckf_api_toolkit/__init__.py
ckf_api_toolkit/aws_dynamo/__init__.py
ckf_api_toolkit/aws_dynamo/condition_expression.py
ckf_api_toolkit/aws_dynamo/constants.py
ckf_api_toolkit/aws_dynamo/converter.py
ckf_api_toolkit/aws_dynamo/expression_attributes.py
ckf_api_toolkit/aws_dynamo/payload_construction.py
ckf_api_toolkit/aws_dynamo/update_expression.py
ckf_api_toolkit/aws_dynamo/overloaded_gsi/__init__.py
ckf_api_toolkit/aws_dynamo/overloaded_gsi/composite_key_utils.py
ckf_api_toolkit/aws_dynamo/overloaded_gsi/payload_factory.py
ckf_api_toolkit/aws_s3/__init__.py
ckf_api_toolkit/aws_s3/s3_constants.py
ckf_api_toolkit/aws_s3/s3_payload_construction.py
ckf_api_toolkit/core/__init__.py
ckf_api_toolkit/http/__init__.py
ckf_api_toolkit/http/requests_payload_construction.py
ckf_api_toolkit/tools/__init__.py
ckf_api_toolkit/tools/error_handling.py
ckf_api_toolkit/tools/general_error.py
ckf_api_toolkit/tools/handler.py
ckf_api_toolkit/tools/logger.py
ckf_api_toolkit/tools/model.py
ckf_api_toolkit/tools/api_response_handler/__init__.py
ckf_api_toolkit/tools/api_response_handler/aws_api_gateway.py
ckf_api_toolkit/tools/api_response_handler/aws_lambda.py
ckf_api_toolkit/tools/csv_writer/__init__.py
ckf_api_toolkit/tools/csv_writer/aws_lambda_s3_csv_writer.py
ckf_api_toolkit-0.7.0.dist-info/LICENSE.txt
ckf_api_toolkit-0.7.0.dist-info/METADATA
ckf_api_toolkit-0.7.0.dist-info/WHEEL
ckf_api_toolkit-0.7.0.dist-info/top_level.txt
ckf_api_toolkit-0.7.0.dist-info/RECORD
