Metadata-Version: 2.1
Name: ckf-api-toolkit
Version: 0.7.0
Summary: Tools for rapid deployment of REST API serverless applications using Python 3.7
Home-page: https://gitlab.com/cloud-kung-fu/ckf-api-toolkit
Author: John Marian
Author-email: john@johninthecloud.com
License: UNKNOWN
Platform: UNKNOWN
Classifier: Programming Language :: Python :: 3
Classifier: License :: OSI Approved :: MIT License
Classifier: Operating System :: OS Independent
Requires-Python: >=3.7
License-File: LICENSE.txt
Requires-Dist: boto3
Requires-Dist: requests
Requires-Dist: deprecation
